coffea/__init__.py
coffea/_version.py
coffea/analysis_tools.py
coffea/util.py
coffea/version.pyi
coffea/btag_tools/__init__.py
coffea/btag_tools/btagscalefactor.py
coffea/dataset_tools/__init__.py
coffea/dataset_tools/apply_processor.py
coffea/dataset_tools/dataset_query.py
coffea/dataset_tools/filespec.py
coffea/dataset_tools/manipulations.py
coffea/dataset_tools/preprocess.py
coffea/dataset_tools/rucio_utils.py
coffea/jetmet_tools/CorrectedJetsFactory.py
coffea/jetmet_tools/CorrectedMETFactory.py
coffea/jetmet_tools/FactorizedJetCorrector.py
coffea/jetmet_tools/JECStack.py
coffea/jetmet_tools/JetCorrectionUncertainty.py
coffea/jetmet_tools/JetResolution.py
coffea/jetmet_tools/JetResolutionScaleFactor.py
coffea/jetmet_tools/__init__.py
coffea/lookup_tools/__init__.py
coffea/lookup_tools/correctionlib_wrapper.py
coffea/lookup_tools/dense_evaluated_lookup.py
coffea/lookup_tools/dense_lookup.py
coffea/lookup_tools/dense_mapped_lookup.py
coffea/lookup_tools/doublecrystalball.py
coffea/lookup_tools/evaluator.py
coffea/lookup_tools/extractor.py
coffea/lookup_tools/jec_uncertainty_lookup.py
coffea/lookup_tools/jersf_lookup.py
coffea/lookup_tools/jme_standard_function.py
coffea/lookup_tools/json_converters.py
coffea/lookup_tools/lookup_base.py
coffea/lookup_tools/rochester_lookup.py
coffea/lookup_tools/root_converters.py
coffea/lookup_tools/txt_converters.py
coffea/lumi_tools/__init__.py
coffea/lumi_tools/lumi_tools.py
coffea/ml_tools/__init__.py
coffea/ml_tools/helper.py
coffea/ml_tools/tf_wrapper.py
coffea/ml_tools/torch_wrapper.py
coffea/ml_tools/triton_wrapper.py
coffea/ml_tools/xgboost_wrapper.py
coffea/nanoevents/__init__.py
coffea/nanoevents/factory.py
coffea/nanoevents/trace.py
coffea/nanoevents/transforms.py
coffea/nanoevents/util.py
coffea/nanoevents/assets/__init__.py
coffea/nanoevents/assets/edm4hep_v00-10-01.yaml
coffea/nanoevents/assets/edm4hep_v00-10-02.yaml
coffea/nanoevents/assets/edm4hep_v00-10-03.yaml
coffea/nanoevents/assets/edm4hep_v00-10-04.yaml
coffea-2025.12.0.dist-info/METADATA
coffea-2025.12.0.dist-info/WHEEL
coffea-2025.12.0.dist-info/licenses/LICENSE
coffea-2025.12.0.dist-info/RECORD
