Metadata-Version: 2.4
Name: coffea
Version: 2025.12.0
Summary: Basic tools and wrappers for enabling not-too-alien syntax when running columnar Collider HEP analysis.
Project-URL: Homepage, https://github.com/coffeateam/coffea
Project-URL: Bug Tracker, https://github.com/coffeateam/coffea/issues
Author-email: Lindsey Gray <lagray@fnal.gov>, Nick Smith <ncsmith@fnal.gov>, Iason Krommydas <ik23@rice.edu>
Maintainer-email: Lindsey Gray <lagray@fnal.gov>, Nick Smith <ncsmith@fnal.gov>, Iason Krommydas <ik23@rice.edu>
License: BSD-3-Clause
License-File: LICENSE
Classifier: Development Status :: 4 - Beta
Classifier: Intended Audience :: Developers
Classifier: Intended Audience :: Information Technology
Classifier: Intended Audience :: Science/Research
Classifier: License :: OSI Approved :: BSD License
Classifier: Operating System :: MacOS
Classifier: Operating System :: Microsoft :: Windows
Classifier: Operating System :: POSIX
Classifier: Operating System :: Unix
Classifier: Programming Language :: Python
Classifier: Programming Language :: Python :: 3
Classifier: Programming Language :: Python :: 3 :: Only
Classifier: Programming Language :: Python :: 3.10
Classifier: Programming Language :: Python :: 3.11
Classifier: Programming Language :: Python :: 3.12
Classifier: Programming Language :: Python :: 3.13
Classifier: Programming Language :: Python :: 3.14
Classifier: Topic :: Scientific/Engineering
Classifier: Topic :: Scientific/Engineering :: Information Analysis
Classifier: Topic :: Scientific/Engineering :: Mathematics
Classifier: Topic :: Scientific/Engineering :: Physics
Classifier: Topic :: Software Development
Classifier: Topic :: Utilities
Requires-Python: >=3.10
Requires-Dist: aiohttp
Requires-Dist: awkward>=2.8.9
Requires-Dist: cachetools
Requires-Dist: cloudpickle>=1.2.3
Requires-Dist: correctionlib>=2.6.0
Requires-Dist: dask-awkward>=2025.9.0
Requires-Dist: dask-histogram>=2025.2.0
Requires-Dist: dask[array]>=2024.3.0
Requires-Dist: fsspec
Requires-Dist: hist>=2
Requires-Dist: ipywidgets
Requires-Dist: loky>=3.5.6
Requires-Dist: lz4
Requires-Dist: matplotlib>=3
Requires-Dist: mplhep>=0.1.18
Requires-Dist: numba>=0.58.1
Requires-Dist: numpy>=1.22
Requires-Dist: packaging
Requires-Dist: pandas
Requires-Dist: pyarrow>=6.0.0
Requires-Dist: pydantic
Requires-Dist: requests
Requires-Dist: rich
Requires-Dist: scipy>=1.1.0
Requires-Dist: toml>=0.10.2
Requires-Dist: tqdm>=4.27.0
Requires-Dist: uproot>=5.6.0
Requires-Dist: vector!=1.6.0,>=1.4.1
Provides-Extra: dask
Requires-Dist: blosc2; extra == 'dask'
Requires-Dist: bokeh!=3.0.*,>=2.4.2; extra == 'dask'
Requires-Dist: distributed>=2024.3.0; extra == 'dask'
Provides-Extra: dev
Requires-Dist: black; extra == 'dev'
Requires-Dist: distributed>=2023.4.0; extra == 'dev'
Requires-Dist: flake8; extra == 'dev'
Requires-Dist: ipython; extra == 'dev'
Requires-Dist: myst-nb; extra == 'dev'
Requires-Dist: nbsphinx; extra == 'dev'
Requires-Dist: pre-commit; extra == 'dev'
Requires-Dist: pydata-sphinx-theme; extra == 'dev'
Requires-Dist: pyinstrument; extra == 'dev'
Requires-Dist: pytest; extra == 'dev'
Requires-Dist: pytest-asyncio; extra == 'dev'
Requires-Dist: pytest-cov; extra == 'dev'
Requires-Dist: pytest-mock; extra == 'dev'
Requires-Dist: pytest-mpl; extra == 'dev'
Requires-Dist: sphinx-automodapi; extra == 'dev'
Requires-Dist: sphinx-copybutton>=0.3.2; extra == 'dev'
Requires-Dist: sphinx-rtd-theme; extra == 'dev'
Requires-Dist: sphinx<8; extra == 'dev'
Provides-Extra: parsl
Requires-Dist: parsl>=2024.12.09; extra == 'parsl'
Provides-Extra: rucio
Requires-Dist: rucio-clients>=32; extra == 'rucio'
Provides-Extra: triton
Requires-Dist: tritonclient[grpc,http]>=2.56.0; extra == 'triton'
Provides-Extra: xrootd
Requires-Dist: fsspec-xrootd>=0.5.1; extra == 'xrootd'
